jqlite/__init__.py
jqlite/__main__.py
jqlite/cli.py
jqlite/core/__init__.py
jqlite/core/context.py
jqlite/core/filters.py
jqlite/core/json_ops.py
jqlite/core/parser.py
jqlite-0.4.3.dist-info/entry_points.txt
jqlite-0.4.3.dist-info/LICENSE
jqlite-0.4.3.dist-info/WHEEL
jqlite-0.4.3.dist-info/METADATA
jqlite-0.4.3.dist-info/RECORD
